youtube_urls_validator/__init__.py
youtube_urls_validator/validator.py
youtube_urls_validator/utils/__init__.py
youtube_urls_validator/utils/exceptions.py
youtube_urls_validator-0.0.1.dist-info/LICENSE
youtube_urls_validator-0.0.1.dist-info/METADATA
youtube_urls_validator-0.0.1.dist-info/WHEEL
youtube_urls_validator-0.0.1.dist-info/top_level.txt
youtube_urls_validator-0.0.1.dist-info/RECORD
