Metadata-Version: 2.1
Name: youtube-urls-validator
Version: 0.0.1
Summary: Validator for YouTube URLs.
Home-page: https://github.com/Wiped-Out/odnoklassniki_urls_validator
Download-URL: https://github.com/Wiped-Out/odnoklassniki_urls_validator/releases/latest
Author: Emir Takhaviev
Author-email: tah116emir@outlook.com
Keywords: python,validation,youtube
Classifier: Development Status :: 3 - Alpha
Classifier: Intended Audience :: Developers
Classifier: Programming Language :: Python :: 3
Classifier: Operating System :: Unix
Classifier: Operating System :: MacOS :: MacOS X
Classifier: Operating System :: Microsoft :: Windows
License-File: LICENSE
